prompt_scanner/__init__.py
prompt_scanner/cli.py
prompt_scanner/decorators.py
prompt_scanner/models.py
prompt_scanner/scanner.py
prompt_scanner/data/content_policies.yaml
prompt_scanner/data/guardrails.yaml
prompt_scanner/data/injection_patterns.yaml
prompt_scanner-0.3.1.dist-info/licenses/LICENSE
prompt_scanner-0.3.1.dist-info/METADATA
prompt_scanner-0.3.1.dist-info/WHEEL
prompt_scanner-0.3.1.dist-info/entry_points.txt
prompt_scanner-0.3.1.dist-info/top_level.txt
prompt_scanner-0.3.1.dist-info/RECORD
