Metadata-Version: 2.4
Name: prompt-scanner
Version: 0.3.1
Summary: Scan prompts for LLMs to ensure content safety and apply guardrails
Home-page: https://github.com/shivama205/prompt-scanner
Author: Shivam Aggarwal
Author-email: Shivam Aggarwal <shivama205@gmail.com>
License-Expression: MIT
Project-URL: Homepage, https://github.com/shivama205/prompt-scanner
Project-URL: Bug Tracker, https://github.com/shivama205/prompt-scanner/issues
Classifier: Development Status :: 4 - Beta
Classifier: Intended Audience :: Developers
Classifier: Programming Language :: Python :: 3
Classifier: Programming Language :: Python :: 3.8
Classifier: Programming Language :: Python :: 3.9
Classifier: Programming Language :: Python :: 3.10
Classifier: Programming Language :: Python :: 3.11
Classifier: Topic :: Software Development :: Libraries :: Python Modules
Classifier: Topic :: Security
Requires-Python: >=3.8
License-File: LICENSE
Requires-Dist: openai>=1.12.0
Requires-Dist: anthropic>=0.15.0
Requires-Dist: pyyaml>=6.0
Requires-Dist: pydantic>=2.0.0
Requires-Dist: requests>=2.31.0
Requires-Dist: python-dotenv>=1.0.0
Dynamic: author
Dynamic: home-page
Dynamic: license-file
Dynamic: requires-python
